mapyllary/__init__.py
mapyllary/api.py
mapyllary-0.0.6.dist-info/LICENSE
mapyllary-0.0.6.dist-info/METADATA
mapyllary-0.0.6.dist-info/WHEEL
mapyllary-0.0.6.dist-info/top_level.txt
mapyllary-0.0.6.dist-info/RECORD
