Metadata-Version: 2.1
Name: mapyllary
Version: 0.0.6
Summary: Unofficial Mapillary API
Home-page: https://github.com/boycetsang/mapyllary/blob/main/README.md
Author: Boyce Tsang
Author-email: boyce.tsang@gmail.com
License: UNKNOWN
Platform: UNKNOWN
Classifier: Programming Language :: Python :: 3
Classifier: License :: OSI Approved :: MIT License
Classifier: Operating System :: OS Independent
Requires-Python: >=3.5
Requires-Dist: absl-py (==0.11.0)
Requires-Dist: argon2-cffi (==20.1.0)
Requires-Dist: astunparse (==1.6.3)
Requires-Dist: attrs (==20.3.0)
Requires-Dist: backcall (==0.2.0)
Requires-Dist: beautifulsoup4 (==4.9.3)
Requires-Dist: bleach (==3.2.1)
Requires-Dist: bs4 (==0.0.1)
Requires-Dist: cachetools (==4.1.1)
Requires-Dist: certifi (==2020.12.5)
Requires-Dist: cffi (==1.14.4)
Requires-Dist: chardet (==3.0.4)
Requires-Dist: colorlog (==4.7.2)
Requires-Dist: cycler (==0.10.0)
Requires-Dist: decorator (==4.4.2)
Requires-Dist: defusedxml (==0.6.0)
Requires-Dist: docutils (==0.16)
Requires-Dist: entrypoints (==0.3)
Requires-Dist: flatbuffers (==1.12)
Requires-Dist: gast (==0.3.3)
Requires-Dist: google-auth (==1.23.0)
Requires-Dist: google-auth-oauthlib (==0.4.1)
Requires-Dist: google-pasta (==0.2.0)
Requires-Dist: grpcio (==1.34.0)
Requires-Dist: h5py (==2.10.0)
Requires-Dist: html5lib (==1.1)
Requires-Dist: idna (==2.10)
Requires-Dist: imageio (==2.9.0)
Requires-Dist: importlib-metadata (==2.1.1)
Requires-Dist: imutils (==0.5.3)
Requires-Dist: ipdb (==0.13.4)
Requires-Dist: ipykernel (==5.4.2)
Requires-Dist: ipython (==7.9.0)
Requires-Dist: ipython-genutils (==0.2.0)
Requires-Dist: ipywidgets (==7.5.1)
Requires-Dist: jedi (==0.17.2)
Requires-Dist: Jinja2 (==2.11.2)
Requires-Dist: joblib (==0.14.1)
Requires-Dist: jsonschema (==3.2.0)
Requires-Dist: jupyter (==1.0.0)
Requires-Dist: jupyter-client (==6.1.7)
Requires-Dist: jupyter-console (==6.1.0)
Requires-Dist: jupyter-core (==4.6.3)
Requires-Dist: Keras (==2.4.3)
Requires-Dist: Keras-Preprocessing (==1.1.2)
Requires-Dist: kiwisolver (==1.1.0)
Requires-Dist: matplotlib (==3.0.3)
Requires-Dist: mistune (==0.8.4)
Requires-Dist: nbconvert (==5.6.1)
Requires-Dist: nbformat (==5.0.8)
Requires-Dist: networkx (==2.4)
Requires-Dist: notebook (==6.1.5)
Requires-Dist: numpy (==1.18.5)
Requires-Dist: oauthlib (==3.1.0)
Requires-Dist: opt-einsum (==3.3.0)
Requires-Dist: overpy (==0.4)
Requires-Dist: opencv-python
Requires-Dist: packaging (==20.8)
Requires-Dist: pandas (==1.0.4)
Requires-Dist: pandocfilters (==1.4.3)
Requires-Dist: parso (==0.7.1)
Requires-Dist: pexpect (==4.8.0)
Requires-Dist: pickleshare (==0.7.5)
Requires-Dist: Pillow
Requires-Dist: pkginfo (==1.7.0)
Requires-Dist: portpicker (==1.3.1)
Requires-Dist: prometheus-client (==0.9.0)
Requires-Dist: prompt-toolkit (==2.0.10)
Requires-Dist: protobuf (==3.14.0)
Requires-Dist: ptyprocess (==0.6.0)
Requires-Dist: pyasn1 (==0.4.8)
Requires-Dist: pyasn1-modules (==0.2.8)
Requires-Dist: pycparser (==2.20)
Requires-Dist: Pygments (==2.7.3)
Requires-Dist: pyparsing (==2.4.7)
Requires-Dist: pyrsistent (==0.17.3)
Requires-Dist: python-dateutil (==2.8.1)
Requires-Dist: pytz (==2020.4)
Requires-Dist: PyYAML (==5.3.1)
Requires-Dist: pyzmq (==20.0.0)
Requires-Dist: readline (==6.2.4.1)
Requires-Dist: readme-renderer (==28.0)
Requires-Dist: requests (==2.25.0)
Requires-Dist: requests-oauthlib (==1.3.0)
Requires-Dist: requests-toolbelt (==0.9.1)
Requires-Dist: rsa (==4.6)
Requires-Dist: scikit-image (==0.15.0)
Requires-Dist: scikit-learn (==0.22.2.post1)
Requires-Dist: scipy (==1.4.1)
Requires-Dist: Send2Trash (==1.5.0)
Requires-Dist: six (==1.15.0)
Requires-Dist: soupsieve (==2.1)
Requires-Dist: tensorboard (==2.4.0)
Requires-Dist: tensorboard-plugin-wit (==1.7.0)
Requires-Dist: tensorflow (==2.3.1)
Requires-Dist: tensorflow-estimator (==2.3.0)
Requires-Dist: termcolor (==1.1.0)
Requires-Dist: terminado (==0.8.3)
Requires-Dist: testpath (==0.4.4)
Requires-Dist: tk (==0.1.0)
Requires-Dist: tornado (==6.1)
Requires-Dist: tqdm (==4.56.0)
Requires-Dist: traitlets (==4.3.3)
Requires-Dist: typing-extensions (==3.7.4.3)
Requires-Dist: urllib3
Requires-Dist: wcwidth (==0.2.5)
Requires-Dist: webencodings (==0.5.1)
Requires-Dist: Werkzeug (==1.0.1)
Requires-Dist: widgetsnbextension (==3.5.1)
Requires-Dist: wrapt (==1.12.1)
Requires-Dist: zipp (==1.2.0)
